limax/__init__.py
limax/commands.py
limax/console.py
limax/example.py
limax/io.py
limax/log.py
limax/model.py
limax/plot.py
limax/resources/processed/example_anonym_2017.json
limax/resources/processed/example_anonym_2017.png
limax/resources/processed/example_anonym_2018.json
limax/resources/processed/example_anonym_2018.png
limax/resources/processed/example_anonym_2022.json
limax/resources/processed/example_anonym_2022.png
limax/resources/processed/patient1.json
limax/resources/processed/patient1.png
limax/resources/processed/patient1.txt
limax/resources/processed/patient2.json
limax/resources/processed/patient2.png
limax/resources/processed/patient3.json
limax/resources/processed/patient3.png
limax/resources/processed/report.tsv
limax/resources/raw/example_anonym_2017.csv
limax/resources/raw/example_anonym_2018.csv
limax/resources/raw/example_anonym_2022.csv
limax/resources/raw/patient1.csv
limax/resources/raw/patient2.csv
limax/resources/raw/patient3.csv
limax-0.4.3.dist-info/LICENSE
limax-0.4.3.dist-info/METADATA
limax-0.4.3.dist-info/WHEEL
limax-0.4.3.dist-info/entry_points.txt
limax-0.4.3.dist-info/top_level.txt
limax-0.4.3.dist-info/zip-safe
limax-0.4.3.dist-info/RECORD
